pypydata/__init__.py
pypydata/command.py
pypydata/list.py
tests/__init__.py
tests/test_list.py
pypydata-1.0.0.dist-info/LICENSE
pypydata-1.0.0.dist-info/METADATA
pypydata-1.0.0.dist-info/WHEEL
pypydata-1.0.0.dist-info/entry_points.txt
pypydata-1.0.0.dist-info/top_level.txt
pypydata-1.0.0.dist-info/RECORD
